order_management_pkg/__init__.py
order_management_pkg/processor.py
order_management_silverstalan-0.1.5.dist-info/METADATA
order_management_silverstalan-0.1.5.dist-info/WHEEL
order_management_silverstalan-0.1.5.dist-info/licenses/LICENSE
order_management_silverstalan-0.1.5.dist-info/RECORD
