Metadata-Version: 2.3
Name: order-management-silverstalan
Version: 0.1.5
Summary: Object-oriented AWS Order Management System with DynamoDB, S3, and SNS integration. Features Order Processor, DynamoDB Handler, Storage Handler, Document Handler (S3), and Notification Service components.
Author-email: silverstalan <your.email@example.com>
Classifier: License :: OSI Approved :: MIT License
Classifier: Operating System :: OS Independent
Classifier: Programming Language :: Python :: 3
Requires-Python: >=3.8
Requires-Dist: boto3>=1.26.0
